MANIFEST.in
README.md
pyproject.toml
setup.py
snphwe/__init__.py
snphwe/hwe.cpp
snphwe/hwe.pyx
snphwe.egg-info/PKG-INFO
snphwe.egg-info/SOURCES.txt
snphwe.egg-info/dependency_links.txt
snphwe.egg-info/top_level.txt
src/snp_hwe.cpp
src/snp_hwe.h
tests/__init__.py
tests/test_hwe.py