Metadata-Version: 2.1
Name: snphwe
Version: 1.1.0
Summary: fast hardy weinberg test
Home-page: https://github.com/jeremymcrae/snphwe
Author: Jeremy McRae (original code by Jan Wiggington)
Author-email: jmcrae@illumina.com
License: MIT
Platform: UNKNOWN
Classifier: Development Status :: 5 - Production/Stable
Classifier: Topic :: Scientific/Engineering :: Bio-Informatics
Classifier: License :: OSI Approved :: MIT License
